Metadata-Version: 2.4
Name: atgtools
Version: 0.1.9
Summary: Add your description here
Requires-Python: <=3.13,>=3.12
License-File: LICENSE
Requires-Dist: adjusttext>=1.3.0
Requires-Dist: anndata>=0.11.4
Requires-Dist: bionumpy>=1.0.14
Requires-Dist: loguru>=0.7.3
Requires-Dist: matplotlib>=3.10.1
Requires-Dist: matplotlib-venn>=1.1.2
Requires-Dist: pandas>=2.2.3
Requires-Dist: psutil>=7.0.0
Requires-Dist: pyfastx>=2.2.0
Requires-Dist: pytest>=8.3.5
Requires-Dist: pytest-cov>=6.1.1
Requires-Dist: requests>=2.32.3
Requires-Dist: rpy2>=3.5.17
Requires-Dist: seaborn>=0.13.2
Requires-Dist: tabulate>=0.9.0
Requires-Dist: tqdm>=4.67.1
Requires-Dist: typer>=0.15.3
Dynamic: license-file
